execexcel/__init__.py
execexcel/handler.py
exec_excel-0.0.1.dist-info/LICENSE
exec_excel-0.0.1.dist-info/METADATA
exec_excel-0.0.1.dist-info/WHEEL
exec_excel-0.0.1.dist-info/top_level.txt
exec_excel-0.0.1.dist-info/RECORD
