Metadata-Version: 2.1
Name: exec-excel
Version: 0.0.1
Summary: Import or export Excel.
Home-page: https://github.com/Supplayer/exec_excel.git
Author: Supplayer
Author-email: x254724521@hotmail.com
License: UNKNOWN
Platform: UNKNOWN
Classifier: Programming Language :: Python :: 3
Classifier: License :: OSI Approved :: MIT License
Classifier: Operating System :: OS Independent
Requires-Python: >=3.6
Requires-Dist: pandas
